webapp_starter/__init__.py
webapp_starter/py.typed
webapp_starter/cli/__init__.py
webapp_starter/cli/backend.py
webapp_starter/cli/webapp.py
webapp_starter/client/__init__.py
webapp_starter/client/client.py
webapp_starter/context/__init__.py
webapp_starter/context/context.py
webapp_starter/main/__init__.py
webapp_starter/main/backend.py
webapp_starter/main/frontend.py
webapp_starter/main/frontend_release.py
webapp_starter/main/main.py
webapp_starter/models/__init__.py
webapp_starter/models/config.py
webapp_starter/models/options.py
webapp_starter/models/path.py
webapp_starter/models/secrets_.py
webapp_starter-0.1.5.dist-info/LICENSE
webapp_starter-0.1.5.dist-info/METADATA
webapp_starter-0.1.5.dist-info/WHEEL
webapp_starter-0.1.5.dist-info/entry_points.txt
webapp_starter-0.1.5.dist-info/top_level.txt
webapp_starter-0.1.5.dist-info/RECORD
