Metadata-Version: 2.1
Name: webapp-starter
Version: 0.1.5
Summary: Template for Python package published on PyPI
Author-email: Quinten Roets <qdr2104@columbia.edu>
License: MIT
Project-URL: Source Code, https://github.com/quintenroets/webapp-starter
Requires-Python: >=3.10
License-File: LICENSE
Requires-Dist: package-utils[context] <1,>=0.6.2
Requires-Dist: powercli <1,>=0.2.0
Requires-Dist: uvicorn <1,>=0.23.2
Provides-Extra: dev
Requires-Dist: python-dotenv <2,>=1.0.1 ; extra == 'dev'
Requires-Dist: package-dev-tools <1,>=0.5.11 ; extra == 'dev'
Requires-Dist: package-dev-utils <1,>=0.1.6 ; extra == 'dev'
Requires-Dist: types-requests <3,>=2.31.0.10 ; extra == 'dev'
